paho1/__init__.py
paho1/mqtt/__init__.py
paho1/mqtt/client.py
paho1/mqtt/matcher.py
paho1/mqtt/packettypes.py
paho1/mqtt/properties.py
paho1/mqtt/publish.py
paho1/mqtt/reasoncodes.py
paho1/mqtt/subscribe.py
paho1/mqtt/subscribeoptions.py
paho_mqtt_old-1.6.2.dist-info/LICENSE.txt
paho_mqtt_old-1.6.2.dist-info/METADATA
paho_mqtt_old-1.6.2.dist-info/WHEEL
paho_mqtt_old-1.6.2.dist-info/notice.html
paho_mqtt_old-1.6.2.dist-info/top_level.txt
paho_mqtt_old-1.6.2.dist-info/RECORD
